{
    "annotations": {
        "list": [
            {
                "builtIn": 1,
                "datasource": {
                    "type": "grafana",
                    "uid": "-- Grafana --"
                },
                "enable": true,
                "hide": true,
                "iconColor": "rgba(0, 211, 255, 1)",
                "name": "Annotations & Alerts",
                "type": "dashboard"
            }
        ]
    },
    "editable": true,
    "fiscalYearStartMonth": 0,
    "graphTooltip": 0,
    "id": 1,
    "links": [],
    "liveNow": false,
    "panels": [
        {
            "datasource": {
                "type": "prometheus",
                "uid": "${DS_PROMETHEUS}"
            },
            "fieldConfig": {
                "defaults": {
                    "color": {
                        "mode": "palette-classic"
                    },
                    "custom": {
                        "axisCenteredZero": false,
                        "axisColorMode": "text",
                        "axisLabel": "",
                        "axisPlacement": "auto",
                        "barAlignment": 0,
                        "drawStyle": "line",
                        "fillOpacity": 10,
                        "gradientMode": "none",
                        "hideFrom": {
                            "legend": false,
                            "tooltip": false,
                            "viz": false
                        },
                        "lineInterpolation": "linear",
                        "lineWidth": 1,
                        "pointSize": 5,
                        "scaleDistribution": {
                            "type": "linear"
                        },
                        "showPoints": "auto",
                        "spanNulls": false,
                        "stacking": {
                            "group": "A",
                            "mode": "none"
                        },
                        "thresholdsStyle": {
                            "mode": "off"
                        }
                    },
                    "mappings": [],
                    "thresholds": {
                        "mode": "absolute",
                        "steps": [
                            {
                                "color": "green",
                                "value": null
                            },
                            {
                                "color": "red",
                                "value": 80
                            }
                        ]
                    }
                },
                "overrides": []
            },
            "gridPos": {
                "h": 8,
                "w": 12,
                "x": 0,
                "y": 0
            },
            "id": 1,
            "options": {
                "legend": {
                    "calcs": [],
                    "displayMode": "list",
                    "placement": "bottom",
                    "showLegend": true
                },
                "tooltip": {
                    "mode": "single",
                    "sort": "none"
                }
            },
            "targets": [
                {
                    "datasource": {
                        "type": "prometheus",
                        "uid": "${DS_PROMETHEUS}"
                    },
                    "expr": "sum(rate(astraguard_anomalies_by_type_total[5m])) by (type)",
                    "refId": "A"
                }
            ],
            "title": "Anomaly Rate (5m)",
            "type": "timeseries"
        },
        {
            "datasource": {
                "type": "prometheus",
                "uid": "${DS_PROMETHEUS}"
            },
            "fieldConfig": {
                "defaults": {
                    "color": {
                        "mode": "thresholds"
                    },
                    "mappings": [],
                    "thresholds": {
                        "mode": "absolute",
                        "steps": [
                            {
                                "color": "green",
                                "value": null
                            },
                            {
                                "color": "red",
                                "value": 1
                            }
                        ]
                    }
                },
                "overrides": []
            },
            "gridPos": {
                "h": 8,
                "w": 12,
                "x": 12,
                "y": 0
            },
            "id": 2,
            "options": {
                "orientation": "auto",
                "reduceOptions": {
                    "calcs": [
                        "lastNotNull"
                    ],
                    "fields": "",
                    "values": false
                },
                "showThresholdLabels": false,
                "text": {}
            },
            "targets": [
                {
                    "datasource": {
                        "type": "prometheus",
                        "uid": "${DS_PROMETHEUS}"
                    },
                    "expr": "max(astraguard_mission_phase) by (phase) == 1",
                    "refId": "A"
                }
            ],
            "title": "Current Mission Phase",
            "type": "gauge"
        },
        {
            "datasource": {
                "type": "prometheus",
                "uid": "${DS_PROMETHEUS}"
            },
            "fieldConfig": {
                "defaults": {
                    "color": {
                        "mode": "palette-classic"
                    },
                    "custom": {
                        "hideFrom": {
                            "legend": false,
                            "tooltip": false,
                            "viz": false
                        }
                    },
                    "mappings": []
                },
                "overrides": []
            },
            "gridPos": {
                "h": 9,
                "w": 24,
                "x": 0,
                "y": 8
            },
            "id": 3,
            "options": {
                "legend": {
                    "calcs": [],
                    "displayMode": "list",
                    "placement": "bottom",
                    "showLegend": true
                },
                "tooltip": {
                    "mode": "single",
                    "sort": "none"
                }
            },
            "targets": [
                {
                    "datasource": {
                        "type": "prometheus",
                        "uid": "${DS_PROMETHEUS}"
                    },
                    "expr": "sum(increase(astraguard_recovery_actions_total[1h])) by (action)",
                    "refId": "A"
                }
            ],
            "title": "Recovery Actions (Last Hour)",
            "type": "barchart"
        }
    ],
    "schemaVersion": 38,
    "style": "dark",
    "tags": [],
    "templating": {
        "list": [
            {
                "description": "Prometheus Datasource",
                "hide": 0,
                "includeAll": false,
                "label": "Datasource",
                "multi": false,
                "name": "DS_PROMETHEUS",
                "options": [],
                "query": "prometheus",
                "refresh": 1,
                "regex": "",
                "skipUrlSync": false,
                "type": "datasource"
            }
        ]
    },
    "time": {
        "from": "now-6h",
        "to": "now"
    },
    "timepicker": {},
    "timezone": "",
    "title": "AstraGuard Mission Control",
    "uid": "ce7i4l0lq7x34e",
    "version": 2,
    "weekStart": ""
}